contexere/__init__.py
contexere/config.py
contexere/context.py
contexere/dataframe.py
contexere/http_client.py
contexere/log.py
contexere/models.py
contexere/op.py
contexere/openai_instrumentation.py
contexere/py.typed
contexere/query.py
contexere_ai-0.3.1.dist-info/METADATA
contexere_ai-0.3.1.dist-info/WHEEL
contexere_ai-0.3.1.dist-info/top_level.txt
contexere_ai-0.3.1.dist-info/RECORD
