Metadata-Version: 2.4
Name: contexere-ai
Version: 0.3.1
Summary: LLM Tracing and Context Engineering for Production AI Agents
Home-page: https://github.com/contexere/contexere
Author: Vitoria
Author-email: vitoria@contexere.ai
Classifier: Development Status :: 3 - Alpha
Classifier: Intended Audience :: Developers
Classifier: Topic :: Software Development :: Libraries :: Python Modules
Classifier: License :: OSI Approved :: MIT License
Classifier: Programming Language :: Python :: 3
Classifier: Programming Language :: Python :: 3.8
Classifier: Programming Language :: Python :: 3.9
Classifier: Programming Language :: Python :: 3.10
Classifier: Programming Language :: Python :: 3.11
Requires-Python: >=3.8
Requires-Dist: httpx>=0.24.0
Requires-Dist: pandas>=1.5.0
Provides-Extra: openai
Requires-Dist: openai>=1.0.0; extra == "openai"
Dynamic: author
Dynamic: author-email
Dynamic: classifier
Dynamic: description
Dynamic: description-content-type
Dynamic: home-page
Dynamic: provides-extra
Dynamic: requires-dist
Dynamic: requires-python
Dynamic: summary
